.gitignore
CHANGELOG.md
LICENSE
MANIFEST.in
Makefile
README.md
mkdocs.yml
requirements-dev.txt
requirements.txt
setup.cfg
setup.py
.github/pull_request_template.md
.github/workflows/python_unittest.yaml
docs/CNAME
docs/changelog.md
docs/index.md
docs/api/index.md
docs/api/utils.md
docs/assets/css/custom.css
docs/assets/images/favicon.ico
docs/assets/images/mypackage.png
examples/README.md
tests/__init__.py
tests/mypackage_test.py
torta/__init__.py
torta/_version.py
torta/utils.py
torta.egg-info/PKG-INFO
torta.egg-info/SOURCES.txt
torta.egg-info/dependency_links.txt
torta.egg-info/top_level.txt