Metadata-Version: 2.1
Name: torta
Version: 0.0.1
Summary: The Torta Ecosystem for Embodied AI
Home-page: https://learnables.github.com/torta
Author: Seb Arnold
Author-email: smr.arnold@gmail.com
License: License :: OSI Approved :: Apache Software License
Download-URL: https://github.com/seba-1511/torta/archive/0.0.1.zip
Platform: UNKNOWN
